LICENSE
README.md
setup.cfg
setup.py
pymonet/__init__.py
pymonet/box.py
pymonet/either.py
pymonet/immutable_list.py
pymonet/lazy.py
pymonet/maybe.py
pymonet/monad_try.py
pymonet/semigroups.py
pymonet/task.py
pymonet/utils.py
pymonet/validation.py
pymonet.egg-info/PKG-INFO
pymonet.egg-info/SOURCES.txt
pymonet.egg-info/dependency_links.txt
pymonet.egg-info/top_level.txt