Metadata-Version: 1.1
Name: pymonet
Version: 0.12.0
Summary: High abstract python library for functional programming. Contains algebraic data structures known from Haskell or Scala.
Home-page: https://github.com/przemyslawjanpietrzak/pyMonet
Author: Przemyslaw Jan Pietrzak
Author-email: przemyslaw.jan.pietrzak@gmail.com
License: UNKNOWN
Download-URL: https://github.com/przemyslawjanpietrzak/pyMonet/archive/0.11.1.tar.gz
Keywords: functional-programming,monads,functors,semigroups
Platform: UNKNOWN
